odoo10_addon_partner_address_two_lines-10.0.1.0.0.99.dev6-py3.8-nspkg.pth
odoo/addons/partner_address_two_lines/README.rst
odoo/addons/partner_address_two_lines/__init__.py
odoo/addons/partner_address_two_lines/__manifest__.py
odoo/addons/partner_address_two_lines/i18n/partner_address_two_lines.pot
odoo/addons/partner_address_two_lines/models/__init__.py
odoo/addons/partner_address_two_lines/models/report.py
odoo/addons/partner_address_two_lines/models/res_partner.py
odoo/addons/partner_address_two_lines/readme/CONTRIBUTORS.rst
odoo/addons/partner_address_two_lines/readme/DESCRIPTION.rst
odoo/addons/partner_address_two_lines/readme/INSTALL.rst
odoo/addons/partner_address_two_lines/static/description/icon.png
odoo/addons/partner_address_two_lines/static/description/index.html
odoo10_addon_partner_address_two_lines-10.0.1.0.0.99.dev6.dist-info/METADATA
odoo10_addon_partner_address_two_lines-10.0.1.0.0.99.dev6.dist-info/WHEEL
odoo10_addon_partner_address_two_lines-10.0.1.0.0.99.dev6.dist-info/namespace_packages.txt
odoo10_addon_partner_address_two_lines-10.0.1.0.0.99.dev6.dist-info/top_level.txt
odoo10_addon_partner_address_two_lines-10.0.1.0.0.99.dev6.dist-info/RECORD
